CHANGELOG.txt
LICENCE.txt
MANIFEST.in
README.md
setup.py
fastapi_auth/__init__.py
fastapi_auth/deps.py
fastapi_auth/schemas.py
fastapi_auth/security.py
fastapi_auth.egg-info/PKG-INFO
fastapi_auth.egg-info/SOURCES.txt
fastapi_auth.egg-info/dependency_links.txt
fastapi_auth.egg-info/requires.txt
fastapi_auth.egg-info/top_level.txt