Metadata-Version: 1.0
Name: fastapi-auth
Version: 0.0.9
Summary: Standard authorization method from fastapi documentation
Home-page: UNKNOWN
Author: Alex Demure
Author-email: alexanderdemure@gmail.com
License: MIT
Keywords: fastapi
Platform: UNKNOWN
